satvatml/1.py
satvatml/2.py
satvatml/3.py
satvatml/4.py
satvatml/5.py
satvatml/6.py
satvatml/7.py
satvatml/8.py
satvatml/9.py
satvatml/__init__.py
your_module-0.1.dist-info/METADATA
your_module-0.1.dist-info/WHEEL
your_module-0.1.dist-info/top_level.txt
your_module-0.1.dist-info/RECORD
